LICENSE
README.md
setup.py
CVE_2021_42063.egg-info/PKG-INFO
CVE_2021_42063.egg-info/SOURCES.txt
CVE_2021_42063.egg-info/dependency_links.txt
CVE_2021_42063.egg-info/entry_points.txt
CVE_2021_42063.egg-info/requires.txt
CVE_2021_42063.egg-info/top_level.txt
cve202142063/__init__.py
cve202142063/main.py
cve202142063/includes/__init__.py
cve202142063/includes/bot.py
cve202142063/includes/filereader.py
cve202142063/includes/scan.py
cve202142063/includes/writefile.py
cve202142063/utils/__init__.py
cve202142063/utils/configure.py
cve202142063/utils/const.py
cve202142063/utils/helpers.py
cve202142063/utils/status.py